setup.cfg
setup.py
nectf_installme/__init__.py
nectf_installme.egg-info/PKG-INFO
nectf_installme.egg-info/SOURCES.txt
nectf_installme.egg-info/dependency_links.txt
nectf_installme.egg-info/top_level.txt