Metadata-Version: 1.0
Name: nectf-installme
Version: 1.0
Summary: Get flagggggggggg!
Home-page: https://github.com/mmdjiji
Author: jiji
Author-email: i@dont.know
License: GPLv3.0
Keywords: nectf,getflag
Platform: all
